CLCR_benchmarks/__init__.py
CLCR_benchmarks/old_benchmark_one.py
CLCR_benchmarks/old_benchmark_two.py
CLCR_benchmarks/toga_analysis.py
CLCR_func/__init__.py
CLCR_func/assembly_healing.py
CLCR_func/inactive_features.py
CLCR_func/maintenance.py
CLCR_func/output_processing.py
CLCR_func/plot_creation.py
CLCR_func/query_creation.py
CLCR_func/slurmarray_creation.py
CLCR-1.0.0.dist-info/LICENSE.txt
CLCR-1.0.0.dist-info/METADATA
CLCR-1.0.0.dist-info/WHEEL
CLCR-1.0.0.dist-info/entry_points.txt
CLCR-1.0.0.dist-info/top_level.txt
CLCR-1.0.0.dist-info/RECORD
