Metadata-Version: 2.1
Name: CLCR
Version: 1.0.0
Summary: Tool fo low coverage region correction
Home-page: https://github.com/Johannes-Zi/CLCR
Author: Johannes Zieres
Author-email: johannes.zieres@gmail.com
License: GPL-3.0
Classifier: Operating System :: POSIX :: Linux
Classifier: Environment :: Console
Classifier: Development Status :: 3 - Alpha
Classifier: Intended Audience :: End Users/Desktop
Classifier: License :: OSI Approved :: GNU General Public License v3 or later (GPLv3+)
Classifier: Natural Language :: English
Classifier: Programming Language :: Python :: 3
Requires-Python: >=3.7.0
License-File: LICENSE.txt
Requires-Dist: pandas
